termtalk/__init__.py
termtalk/alr.py
termtalk/config.json
termtalk/credential.json
termtalk/exitHandler.py
termtalk/exit_flag
termtalk/lio.py
termtalk/main.py
termtalk/messagehandler.py
termtalk/peler.py
termtalk/receiver.py
termtalk/sender.py
termtalk-1.0.0.dist-info/METADATA
termtalk-1.0.0.dist-info/WHEEL
termtalk-1.0.0.dist-info/entry_points.txt
termtalk-1.0.0.dist-info/top_level.txt
termtalk-1.0.0.dist-info/RECORD
