Metadata-Version: 2.1
Name: termtalk
Version: 1.0.0
Summary: Use to chat with Public random on Terminal
Author: Dzadafa
Author-email: Dzakwan Daris <dzakwandarisfakhruddin@gmail.com>
License: MIT Licencse
Classifier: Programming Language :: Python :: 3
Classifier: License :: OSI Approved :: MIT License
Classifier: Operating System :: OS Independent
Requires-Dist: pyrebase4 >=4.8.0
Requires-Dist: windows-curses >=2.3.3 ; platform_system == "Windows"
